{"nodes": [{"id": "index", "label": "index.ts", "file_type": "code", "source_file": "packages/ui/src/toolbar/index.ts", "source_location": "L1"}], "edges": [{"source": "index", "target": "toolbar_root_svelte", "relation": "imports_from", "confidence": "EXTRACTED", "source_file": "packages/ui/src/toolbar/index.ts", "source_location": "L8", "weight": 1.0}, {"source": "index", "target": "toolbar_button_svelte", "relation": "imports_from", "confidence": "EXTRACTED", "source_file": "packages/ui/src/toolbar/index.ts", "source_location": "L9", "weight": 1.0}, {"source": "index", "target": "toolbar_separator_svelte", "relation": "imports_from", "confidence": "EXTRACTED", "source_file": "packages/ui/src/toolbar/index.ts", "source_location": "L10", "weight": 1.0}, {"source": "index", "target": "toolbar_link_svelte", "relation": "imports_from", "confidence": "EXTRACTED", "source_file": "packages/ui/src/toolbar/index.ts", "source_location": "L11", "weight": 1.0}]}