{"nodes": [{"id": "data_grid_root_svelte_d", "label": "data-grid-root.svelte.d.ts", "file_type": "code", "source_file": "packages/primitives/src/data-grid/data-grid-root.svelte.d.ts", "source_location": "L1"}, {"id": "data_grid_root_svelte_d_sveltets_render", "label": "__sveltets_Render", "file_type": "code", "source_file": "packages/primitives/src/data-grid/data-grid-root.svelte.d.ts", "source_location": "L17"}], "edges": [{"source": "data_grid_root_svelte_d", "target": "svelte", "relation": "imports_from", "confidence": "EXTRACTED", "source_file": "packages/primitives/src/data-grid/data-grid-root.svelte.d.ts", "source_location": "L1", "weight": 1.0}, {"source": "data_grid_root_svelte_d", "target": "elements", "relation": "imports_from", "confidence": "EXTRACTED", "source_file": "packages/primitives/src/data-grid/data-grid-root.svelte.d.ts", "source_location": "L2", "weight": 1.0}, {"source": "data_grid_root_svelte_d", "target": "data_grid_root_svelte_d_sveltets_render", "relation": "contains", "confidence": "EXTRACTED", "source_file": "packages/primitives/src/data-grid/data-grid-root.svelte.d.ts", "source_location": "L17", "weight": 1.0}]}